home/__init__.py
home/__main__.py
home/configs.py
home/logger.py
home/my_home.py
home/options.py
home/performer.py
home/process.py
home/appliance/__init__.py
home/appliance/callable.py
home/appliance/collection.py
home/appliance/data.py
home/appliance/event.py
home/appliance/state.py
home/appliance/attribute/__init__.py
home/appliance/attribute/mixin.py
home/appliance/curtain/__init__.py
home/appliance/curtain/event/__init__.py
home/appliance/curtain/event/forced/__init__.py
home/appliance/curtain/event/forced/event.py
home/appliance/curtain/indoor/__init__.py
home/appliance/curtain/indoor/blackout/__init__.py
home/appliance/curtain/indoor/blackout/state/__init__.py
home/appliance/curtain/indoor/blackout/state/closed/__init__.py
home/appliance/curtain/indoor/blackout/state/closed/callable.py
home/appliance/curtain/indoor/blackout/state/closed/state.py
home/appliance/curtain/indoor/blackout/state/forced/__init__.py
home/appliance/curtain/indoor/blackout/state/forced/closed/__init__.py
home/appliance/curtain/indoor/blackout/state/forced/closed/callable.py
home/appliance/curtain/indoor/blackout/state/forced/closed/state.py
home/appliance/curtain/indoor/blackout/state/forced/opened/__init__.py
home/appliance/curtain/indoor/blackout/state/forced/opened/callable.py
home/appliance/curtain/indoor/blackout/state/forced/opened/state.py
home/appliance/curtain/indoor/blackout/state/opened/__init__.py
home/appliance/curtain/indoor/blackout/state/opened/callable.py
home/appliance/curtain/indoor/blackout/state/opened/state.py
home/appliance/curtain/outdoor/__init__.py
home/appliance/curtain/outdoor/bedroom/__init__.py
home/appliance/curtain/outdoor/bedroom/state/__init__.py
home/appliance/curtain/outdoor/bedroom/state/closed/__init__.py
home/appliance/curtain/outdoor/bedroom/state/closed/callable.py
home/appliance/curtain/outdoor/bedroom/state/closed/state.py
home/appliance/curtain/outdoor/bedroom/state/forced/__init__.py
automate_home-0.9.1.dist-info/COPYING
automate_home-0.9.1.dist-info/METADATA
automate_home-0.9.1.dist-info/WHEEL
automate_home-0.9.1.dist-info/top_level.txt
automate_home-0.9.1.dist-info/RECORD
