Metadata-Version: 2.1
Name: automate-home
Version: 0.9.1
Summary: A python3 library to automate (home) devices
Home-page: https://github.com/majamassarini/automate-home
Author: Maja Massarini
Author-email: maja.massarini@gmail.com
License: GPLv3
Platform: UNKNOWN
Classifier: Development Status :: 3 - Alpha
Classifier: License :: OSI Approved :: GNU General Public License v3 (GPLv3)
Classifier: Operating System :: POSIX :: Linux
Classifier: Programming Language :: Python :: 3.8
Classifier: Topic :: Communications
Classifier: Intended Audience :: Developers
License-File: COPYING
Requires-Dist: APScheduler
Requires-Dist: hiredis
Requires-Dist: aioredis (==1.3.1)
Requires-Dist: pyephem
Requires-Dist: pytz
Requires-Dist: PyYAML
